bbscrap/__init__.py
bbscrap/cli.py
bbscrap/main.py
bbscrap/navegacao/__init__.py
bbscrap/navegacao/dependente.py
bbscrap/navegacao/drivers.py
bbscrap/navegacao/lerofx.py
bbscrap/navegacao/login.py
bbscrap/navegacao/nav_cartao.py
bbscrap/navegacao/nav_corrente.py
bbscrap/navegacao/nav_pagina.py
bbscrap/navegacao/nav_poupanca.py
bbscrap/tratamento/altera_variaveis.py
bbscrap/tratamento/chave_unica.py
bbscrap/tratamento/cria_variaveis.py
bbscrap/tratamento/memo_divisao.py
bbscrap/utils/__init__.py
bbscrap/utils/append.py
bbscrap/utils/arquivo.py
bbscrap/utils/data_functions.py
bbscrap/utils/sistema.py
bbscrap-4.2.1.dist-info/entry_points.txt
bbscrap-4.2.1.dist-info/LICENSE
bbscrap-4.2.1.dist-info/WHEEL
bbscrap-4.2.1.dist-info/METADATA
bbscrap-4.2.1.dist-info/RECORD
