Metadata-Version: 2.1
Name: bbscrap
Version: 4.2.1
Summary: Baixa extatos bancários do Banco do Brasil
Author: Vinicius Maciel
Requires-Python: >=3.9,<4.0
Classifier: Programming Language :: Python :: 3
Classifier: Programming Language :: Python :: 3.10
Classifier: Programming Language :: Python :: 3.9
Requires-Dist: ofxparse (>=0.21,<0.22)
Requires-Dist: pandas (>=1.4.1,<2.0.0)
Requires-Dist: selenium (>=4.1.2,<5.0.0)
